nova_api/__init__.py
nova_api/auth.py
nova_api/baseapi.py
nova_api/entity.py
nova_api/dao/__init__.py
nova_api/dao/generic_sql_dao.py
nova_api/dao/mongo_dao.py
nova_api/exceptions/__init__.py
nova_api/persistence/__init__.py
nova_api/persistence/mysql_helper.py
nova_api/persistence/mysql_pool.py
nova_api/persistence/postgresql_helper.py
nova_api/persistence/postgresql_pool.py
nova_api/validations/__init__.py
NovaAPI-0.2.3.post1.dist-info/LICENSE
NovaAPI-0.2.3.post1.dist-info/METADATA
NovaAPI-0.2.3.post1.dist-info/WHEEL
NovaAPI-0.2.3.post1.dist-info/entry_points.txt
NovaAPI-0.2.3.post1.dist-info/top_level.txt
NovaAPI-0.2.3.post1.dist-info/RECORD
