Metadata-Version: 2.1
Name: NovaAPI
Version: 0.2.3.post1
Summary: A package to accelerate REST API development
Home-page: https://github.com/novaweb-mobi/nova-api
Author: Mateus Berardo & Fábio Trevizolo
Author-email: mateust@novaweb.mobi, fabiots@novaweb.mobi
License: MIT
Classifier: Programming Language :: Python :: 3
Classifier: Operating System :: OS Independent
Requires-Python: >=3.7
License-File: LICENSE
Requires-Dist: mysql-connector-python
Requires-Dist: flask
Requires-Dist: flask-cors
Requires-Dist: connexion[swagger-ui]
Requires-Dist: python-jose (>=3.2.0)
Requires-Dist: makefun
Provides-Extra: mongo
Requires-Dist: pymongo (<4.0,>=3.12) ; extra == 'mongo'
Requires-Dist: python-dateutil ; extra == 'mongo'
Provides-Extra: postgresql
Requires-Dist: psycopg2-binary ; extra == 'postgresql'
